Metadata-Version: 1.1
Name: letmecrawl
Version: 0.0.4
Summary: let me crawl
Home-page: https://github.com/montenegrodr/letmecrawl
Author: Robson Montenegro
Author-email: montenegrodr@gmail.com
License: MIT
Download-URL: https://github.com/montenegrodr/letmecrawl/archive/0.0.4.tar.gz
Keywords: scrape crawl
Platform: UNKNOWN
Classifier: Programming Language :: Python :: 2.7
